AUTHORS
ChangeLog
LICENSE
Makefile
README.md
requirements.txt
setup.cfg
setup.py
webdriver_wharf/__init__.py
webdriver_wharf/app.py
webdriver_wharf/cli.py
webdriver_wharf/db.py
webdriver_wharf/interactions.py
webdriver_wharf/worker.py
webdriver_wharf.egg-info/PKG-INFO
webdriver_wharf.egg-info/SOURCES.txt
webdriver_wharf.egg-info/dependency_links.txt
webdriver_wharf.egg-info/entry_points.txt
webdriver_wharf.egg-info/not-zip-safe
webdriver_wharf.egg-info/pbr.json
webdriver_wharf.egg-info/requires.txt
webdriver_wharf.egg-info/top_level.txt