Metadata-Version: 1.1
Name: webdriver-wharf
Version: 0.4.0
Summary: A docker-based warehouse of Selenium servers running chrome and firefox
Home-page: UNKNOWN
Author: Sean Myers
Author-email: sean.myers@redhat.com
License: MIT
Keywords: setup
Platform: UNKNOWN
Classifier: Development Status :: 4 - Beta
Classifier: Environment :: Console
Classifier: Intended Audience :: System Administrators
Classifier: License :: OSI Approved :: MIT License
Classifier: Operating System :: OS Independent
Classifier: Programming Language :: Python :: 2
Classifier: Programming Language :: Python :: 2.7
Classifier: Topic :: System :: Systems Administration
Classifier: Topic :: Utilities
